elasticsearch1/__init__.py
elasticsearch1/compat.py
elasticsearch1/connection_pool.py
elasticsearch1/exceptions.py
elasticsearch1/serializer.py
elasticsearch1/transport.py
elasticsearch1/client/__init__.py
elasticsearch1/client/cat.py
elasticsearch1/client/cluster.py
elasticsearch1/client/indices.py
elasticsearch1/client/nodes.py
elasticsearch1/client/snapshot.py
elasticsearch1/client/utils.py
elasticsearch1/connection/__init__.py
elasticsearch1/connection/base.py
elasticsearch1/connection/http_requests.py
elasticsearch1/connection/http_urllib3.py
elasticsearch1/connection/pooling.py
elasticsearch1/helpers/__init__.py
elasticsearch1/helpers/test.py
elasticsearch1-1.10.0.dist-info/DESCRIPTION.rst
elasticsearch1-1.10.0.dist-info/METADATA
elasticsearch1-1.10.0.dist-info/RECORD
elasticsearch1-1.10.0.dist-info/WHEEL
elasticsearch1-1.10.0.dist-info/metadata.json
elasticsearch1-1.10.0.dist-info/top_level.txt
